{"code": "BMRCOTE-02-01", "code_cote": "02", "url_meteofrance": "https://meteofrance.com/meteo-marine/frontiere-espagnole-port-camargue/BMSCOTE-02-01", "nom": "De la fronti\u00e8re espagnole \u00e0 Port Camargue", "map_filename": "", "map_url": "", "titre": "Bulletin c\u00f4te \"Fronti\u00e8re espagnole - Port Camargue\" soir", "chapeau": "Origine M\u00e9t\u00e9o-France. \nBulletin c\u00f4tier pour la bande des 20 milles, de la fronti\u00e8re espagnole \u00e0 Port-Camargue, du jeudi 30 septembre 2021 \u00e0 18H15 l\u00e9gales.", "avis_special": "Pas d'avis de vent fort en cours ni pr\u00e9vu.", "echeances": [{"titre": "Situation g\u00e9n\u00e9rale le jeudi 30 septembre 2021 \u00e0 12H00 UTC, et \u00e9volution", "regions": [{"situation": "Hautes pressions 1020 \u00e0 1025 hPa sur le bassin."}]}, {"titre": "Observations le jeudi 30 septembre 2021 \u00e0 15H00 UTC", "regions": [{"observations": [{"observation": "Pas d'observations disponibles."}]}]}, {"titre": "Pr\u00e9visions pour la nuit du jeudi 30 septembre au vendredi 1 octobre", "regions": [{"previsions": {"vent": "Nord \u00e0 Nord-Ouest 3 \u00e0 5, mollissant 2 \u00e0 4 en fin de nuit.", "mer": "belle \u00e0 peu agit\u00e9e.", "houle": "non significative.", "temps": "peu nuageux.", "visibilite": "bonne."}}]}, {"titre": "Pr\u00e9visions pour la journ\u00e9e du vendredi 1 octobre", "regions": [{"previsions": {"vent": "Nord \u00e0 Nord-Est 2 \u00e0 4, devenant Variable 1 \u00e0 3 l'apr\u00e8s-midi.", "mer": "belle.", "houle": "non significative.", "temps": "d\u00e9gradation nuageuse en fin d'apr\u00e8s-midi.", "visibilite": "bonne."}}]}, {"titre": "Tendance pour la nuit du 1  au 2, et la journ\u00e9e du samedi 2 octobre", "regions": [{"previsions": {"vent": "variable 2 \u00e0 4, passag\u00e8rement Nord-Ouest 3 \u00e0 4 la nuit, s'orientant Sud-Est 3 \u00e0 5 l'apr\u00e8s-midi, mais 5 \u00e0 6 au sud de Leucate.", "mer": "belle \u00e0 peu agit\u00e9e.", "houle": "non significative.", "temps": "nuages et \u00e9claircies.", "visibilite": "bonne."}}]}], "pied": "Prochain bulletin le vendredi 1 octobre 2021, vers 06H15 l\u00e9gales"}