{"code": "BMRCOTE-02-02", "code_cote": "02", "url_meteofrance": "https://meteofrance.com/meteo-marine/port-camargue-saint-raphael/BMSCOTE-02-02", "nom": "De Port Camargue \u00e0 Saint-Rapha\u00ebl", "map_filename": "cote-02-02.png", "map_url": "https://umap.openstreetmap.fr/en/map/port-camargue-a-sainte-maxime_659137#", "titre": "Bulletin c\u00f4te \"Port Camargue - Saint Rapha\u00ebl\" midi", "chapeau": "Origine M\u00e9t\u00e9o-France. \nBulletin c\u00f4tier pour la bande des 20 milles, de Port-Camargue \u00e0 Saint-Rapha\u00ebl, du mercredi 29 septembre 2021 \u00e0 12H30 l\u00e9gales.", "avis_special": "Avis de Grand Frais \u00e0 coup de vent Nr 361 pour PROVENCE, CORSE.", "echeances": [{"titre": "Situation g\u00e9n\u00e9rale le mercredi 29 septembre 2021 \u00e0 06H00 UTC, et \u00e9volution", "regions": [{"situation": "Perturbation aujourd'hui sur la France puis dorsale se renfor\u00e7ant sur le pays. D\u00e9pression relative se creusant 1015 hPa en mer Ligure, se comble demain en Tyrrh\u00e9nienne."}]}, {"titre": "Observations le mercredi 29 septembre 2021 \u00e0 09H00 UTC", "regions": [{"observations": [{"observation": "Cap Camarat : vent Ouest-Nord-Ouest 8 n\u0153uds, rafales 25 n\u0153uds.\nCap Cepet : vent Nord-Ouest 23 n\u0153uds, rafales 33 n\u0153uds.\nPorquerolles : vent Ouest 21 n\u0153uds.\nCap Couronne : vent Nord-Ouest 17 n\u0153uds, rafales 27 n\u0153uds,  mer peu agit\u00e9e,  visibilit\u00e9 9 milles."}]}]}, {"titre": "Pr\u00e9visions pour l'apr\u00e8s-midi du mercredi 29 septembre", "regions": [{"previsions": {"vent": " Ouest \u00e0 Nord-Ouest 5 \u00e0 6, localement 7 de Sici\u00e9 au Levant. Rafales.", "mer": "agit\u00e9e, devenant localement forte \u00e0 l'est de Sici\u00e9.", "houle": "Sud-Ouest 0.5 \u00e0 1 m, s'amplifiant localement 1.5 m \u00e0 l'est du Levant \u00e0 la fin.", "temps": "ensoleill\u00e9.", "visibilite": "bonne."}}]}, {"titre": "Pr\u00e9visions pour la nuit du mercredi 29 septembre au jeudi 30 septembre", "regions": [{"previsions": {"vent": "- \u00e0 l'ouest de Porquerolles : Nord-Ouest 5 \u00e0 6, mais 7 \u00e0 8 \u00e0 l'est de Beauduc. Rafales.\n- \u00e0 l'est de Porquerolles : Nord \u00e0 Nord-Ouest 5 \u00e0 6, mollissant 3 \u00e0 4 pass\u00e9 minuit.", "mer": "peu agit\u00e9e \u00e0 agit\u00e9e, localement forte du Cap Croisette au Levant.", "houle": "Ouest \u00e0 Sud-Ouest 0.5 \u00e0 1 m, localement 1.5 \u00e0 2 m \u00e0 l'est de Sici\u00e9.", "temps": "clair \u00e0 peu nuageux.", "visibilite": "bonne."}}]}, {"titre": "Pr\u00e9visions pour la journ\u00e9e du jeudi 30 septembre", "regions": [{"previsions": {"vent": "\n- \u00e0 l'ouest de Sici\u00e9 : Nord-Ouest 5 \u00e0 6, localement 7 de Cap Couronne \u00e0 Cap Croisette au d\u00e9but, mollissant progressivement 3 \u00e0 4.\n- \u00e0 l'est de Sici\u00e9 : Nord \u00e0 Nord-Ouest 3 \u00e0 4, virant Est \u00e0 Nord-Est 2 \u00e0 3 l'apr\u00e8s-midi.", "mer": "peu agit\u00e9e \u00e0 agit\u00e9e, devenant belle \u00e0 peu agit\u00e9e l'apr\u00e8s-midi.", "houle": "Ouest 1 \u00e0 2 m \u00e0 l'est de Sici\u00e9, s'amortissant lentement.", "temps": "soleil pr\u00e9dominant.", "visibilite": "bonne."}}]}, {"titre": "Tendance pour la nuit du 30  au 1, et la journ\u00e9e du vendredi 1 octobre", "regions": [{"previsions": {"vent": "\n- \u00e0 l'ouest de Beauduc : Nord 3 \u00e0 4 la nuit, Variable 1 \u00e0 3 en journ\u00e9e.\n- \u00e0 l'est de Beauduc : secteur Est 2 \u00e0 4 la nuit, 3 \u00e0 5 en journ\u00e9e.", "mer": "belle \u00e0 peu agit\u00e9e.", "houle": "rapidement non significative, puis secteur Est 0.5 \u00e0 1 m en journ\u00e9e.", "temps": "beau temps, se voilant l'apr\u00e8s-midi.", "visibilite": "bonne."}}]}], "pied": "Prochain bulletin le mercredi 29 septembre 2021, vers 18H15 l\u00e9gales"}