{"code": "BMRCOTE-02-01", "code_cote": "02", "url_meteofrance": "https://meteofrance.com/meteo-marine/frontiere-espagnole-port-camargue/BMSCOTE-02-01", "nom": "De la fronti\u00e8re espagnole \u00e0 Port Camargue", "map_filename": "", "map_url": "", "titre": "Bulletin c\u00f4te \"Fronti\u00e8re espagnole - Port Camargue\" soir", "chapeau": "Origine M\u00e9t\u00e9o-France. \nBulletin c\u00f4tier pour la bande des 20 milles, de la fronti\u00e8re espagnole \u00e0 Port-Camargue, du mercredi 10 novembre 2021 \u00e0 18H15 l\u00e9gales.", "avis_special": "Avis de grand frais \u00e0 coup de vent nr 436 pour PROVENCE, COTE D\u2019AZUR.", "echeances": [{"titre": "Situation g\u00e9n\u00e9rale le mercredi 10 novembre 2021 \u00e0 12H00 UTC, et \u00e9volution", "regions": [{"situation": "D\u00e9pression orageuse BLAS 1007 hPa entre Majorque et les c\u00f4tes alg\u00e9riennes, se d\u00e9calant lentement vers le nord, pr\u00e9vue sur les \u00eeles Bal\u00e9ares demain matin."}]}, {"titre": "Observations le mercredi 10 novembre 2021 \u00e0 15H00 UTC", "regions": [{"observations": [{"observation": "S\u00e8te : vent Nord-Nord-Est 19 n\u0153uds, rafales 29 n\u0153uds,  mer peu agit\u00e9e,  1017 hPa en baisse,  couvert, pluies ou bruines,  visibilit\u00e9 8 milles.\nCap B\u00e9ar : vent Nord-Ouest 19 n\u0153uds, rafales 39 n\u0153uds,  1018 hPa en hausse.\nLeucate : vent Nord-Ouest 16 n\u0153uds, rafales 31 n\u0153uds,  1018 hPa en baisse.\nEspiguette : vent Nord-Nord-Est 8 n\u0153uds,  visibilit\u00e9 8 milles."}]}]}, {"titre": "Pr\u00e9visions pour la nuit du mercredi 10 novembre au jeudi 11 novembre", "regions": [{"previsions": {"vent": "Nord \u00e0 Nord-Est 4 \u00e0 5, localement 6 pr\u00e8s de la c\u00f4te Vermeille.", "mer": "agit\u00e9e \u00e0 forte.", "houle": "secteur Est 1.5 \u00e0 2.5 m.", "temps": "pluie.", "visibilite": "moyenne \u00e0 mauvaise sous pluie."}}]}, {"titre": "Pr\u00e9visions pour la journ\u00e9e du jeudi 11 novembre", "regions": [{"previsions": {"vent": "Nord \u00e0 Nord-Est 4 \u00e0 5, mollissant 3 \u00e0 4 l'apr\u00e8s-midi, localement 5 pr\u00e8s de la c\u00f4te Vermeille.", "mer": "agit\u00e9e.", "houle": "secteur Est 1 \u00e0 2 m.", "temps": "pluie.", "visibilite": "moyenne sous pluie."}}]}, {"titre": "Tendance pour la nuit du 11 au 12, et la journ\u00e9e du vendredi 12 novembre", "regions": [{"previsions": {"vent": "revenant Nord \u00e0 Nord-Ouest 3 \u00e0 4, fra\u00eechissant 4 \u00e0 5 en fin de nuit, puis localement 6 pr\u00e8s de la c\u00f4te Vermeille le matin.", "mer": "peu agit\u00e9e \u00e0 agit\u00e9e.", "houle": "secteur Sud-Est 1 m.", "temps": "pluie.", "visibilite": "moyenne sous pluie."}}]}], "pied": "Prochain bulletin le jeudi 11 novembre 2021, vers 06H15 l\u00e9gales"}