{"code": "BMRCOTE-01-03", "code_cote": "01", "url_meteofrance": "https://meteofrance.com/meteo-marine/cap-de-la-hague-penmarc-h/BMSCOTE-01-03", "nom": "Du cap de La Hague \u00e0 Penmarc\u2019h", "map_filename": "", "map_url": "", "titre": "Bulletin c\u00f4te \"La Hague \u2013 Penmarc'h\" matin", "chapeau": "Origine M\u00e9t\u00e9o-France. \nBulletin c\u00f4tier pour la bande des 20 milles, du cap de la Hague \u00e0 la pointe de Penmarc'h, du samedi 9 octobre 2021 \u00e0 06H15 l\u00e9gales.", "avis_special": "Pas d'avis de vent fort en cours ni pr\u00e9vu.", "echeances": [{"titre": "Situation g\u00e9n\u00e9rale le samedi 9 octobre 2021 \u00e0 00H00 UTC, et \u00e9volution", "regions": [{"situation": "Dorsale du Danemark \u00e0 la Manche, se d\u00e9calant sur les \u00eeles britanniques en journ\u00e9e, puis Anticyclone 1035 hPa au sud-est de l'Irlande ce soir, g\u00e9n\u00e9rant un flux de Nord-Est."}]}, {"titre": "Observations le samedi 9 octobre 2021 \u00e0 03H00 UTC", "regions": [{"observations": [{"observation": "Ouessant : vent Sud-Est 8 n\u0153uds,  1026 hPa en baisse.\nBatz : vent Est 4 n\u0153uds.\nBrignogan : vent Sud-Est 2 n\u0153uds.\nBr\u00e9hat : vent Est-Sud-Est 8 n\u0153uds.\nCap de la Hague : vent Est-Sud-Est 6 n\u0153uds,  1027 hPa en baisse.\nPointe du Raz : vent Est-Sud-Est 8 n\u0153uds."}]}]}, {"titre": "Pr\u00e9visions pour la journ\u00e9e du samedi 9 octobre", "regions": [{"previsions": {"vent": "Secteur Est 2 \u00e0 3, fra\u00eechissant Nord \u00e0 Nord-Est 3 \u00e0 4 l'apr\u00e8s-midi.", "mer": "\n- de La Hague \u00e0 Perros-Guirec : belle \u00e0 peu agit\u00e9e.\n- de Perros-Guirec \u00e0 Penmarc'h : agit\u00e9e.", "houle": "\n- de La Hague \u00e0 Br\u00e9hat : Ouest 0.5 \u00e0 1 m.\n- de Br\u00e9hat \u00e0 Penmarc'h : Ouest 1 \u00e0 2 m.", "temps": "peu nuageux \u00e0 nuageux, brumeux le matin.", "visibilite": "bonne, localement mauvaise par brume."}}]}, {"titre": "Pr\u00e9visions pour la nuit du samedi 9 octobre au dimanche 10 octobre", "regions": [{"previsions": {"vent": "Nord \u00e0 Nord-Est 3 \u00e0 4.", "mer": "\n- de La Hague \u00e0 Perros-Guirec : belle \u00e0 peu agit\u00e9e.\n- de Perros-Guirec \u00e0 Penmarc'h : peu agit\u00e9e \u00e0 agit\u00e9e.", "houle": "Ouest 0.5 \u00e0 1.5 m.", "temps": "nuageux, quelques bancs de brume.", "visibilite": "bonne, localement mauvaise par brume."}}]}, {"titre": "Tendance pour la journ\u00e9e du dimanche 10 octobre", "regions": [{"previsions": {"vent": "Nord-Est 3 \u00e0 4, fra\u00eechissant 4 \u00e0 5 sur la pointe Bretagne l'apr\u00e8s-midi.", "mer": "\n- de La Hague \u00e0 Perros-Guirec : belle \u00e0 peu agit\u00e9e.\n- de Perros-Guirec \u00e0 Penmarc'h : peu agit\u00e9e \u00e0 agit\u00e9e.", "houle": "Ouest 0.5 \u00e0 1 m.", "temps": "nuageux, quelques bancs de brume le matin.", "visibilite": "bonne, localement mauvaise par brume le matin."}}]}], "pied": "Prochain bulletin le samedi 9 octobre 2021, vers 12H30 l\u00e9gales"}