[{"code": "BMSCOTE-01", "code_cote": "01", "titre": "BMS COTE ATLANTIQUE", "numero": "116", "type_avis": "avis de grand frais", "blocs": [{"code": "BMSCOTE-01-01", "titre": "De la fronti\u00e8re Belge \u00e0 la baie de Somme", "begin_time": "2021-09-28 21:00:00+00:00", "end_time": "2021-09-29 03:00:00+00:00", "texts": ["Valable du mardi 28 septembre \u00e0 21H00 UTC au mercredi 29 septembre \u00e0 03H00 UTC", "VENT : Sud \u00e0 Sud-Ouest 7. Rafales"]}]}, {"code": "BMSCOTE-01", "code_cote": "01", "titre": "BMS COTE ATLANTIQUE", "numero": "145", "type_avis": "avis de grand frais", "blocs": [{"code": "BMSCOTE-01-02", "titre": "de la baie de Somme \u00e0 la Hague.", "begin_time": "2021-09-28 15:00:00+00:00", "end_time": "2021-09-29 03:00:00+00:00", "texts": ["Valable du mardi 28 septembre \u00e0 15H00 UTC au mercredi 29 septembre \u00e0 03H00 UTC", "VENT : Sud-Ouest 7. Rafales"]}]}, {"code": "BMSCOTE-01", "code_cote": "01", "titre": "BMS COTE ATLANTIQUE", "numero": "167", "type_avis": "avis de grand frais", "blocs": [{"code": "BMSCOTE-01-03", "titre": "sur ouest Cotentin", "begin_time": "2021-09-28 15:00:00+00:00", "end_time": "2021-09-28 23:00:00+00:00", "texts": ["Valable du mardi 28 septembre \u00e0 15H00 UTC au mardi 28 septembre \u00e0 23H00 UTC", "VENT : Sud-Ouest 7. Rafales"]}]}, {"code": "BMSCOTE-02", "code_cote": "02", "titre": "BMS COTE MEDITERRANEE", "numero": "358", "type_avis": "Avis de grand frais", "blocs": [{"code": "BMSCOTE-02-01", "titre": "LANGUEDOC-ROUSSILLON : de Cerb\u00e8re \u00e0 Gruissan.", "begin_time": "2021-09-29 02:00:00+00:00", "end_time": "2021-09-29 08:00:00+00:00", "texts": ["Valable du mercredi 29 septembre \u00e0 02H00 UTC au mercredi 29 septembre \u00e0 08H00 UTC", "VENT : Nord-Ouest 7. Rafales"]}]}]