[{"code": "BMRCOTE-01-01", "code_cote": "01", "url_meteofrance": "https://meteofrance.com/meteo-marine/frontiere-belge-baie-de-somme/BMSCOTE-01-01", "nom": "De la fronti\u00e8re belge \u00e0 la baie de Somme", "map_filename": "", "map_url": "", "titre": "Bulletin c\u00f4te \"Fronti\u00e8re belge - Baie de Somme\" midi", "chapeau": "Origine M\u00e9t\u00e9o-France. \nBulletin c\u00f4tier pour la bande des 20 milles, de la fronti\u00e8re belge \u00e0 la baie de Somme, du jeudi 21 octobre 2021 \u00e0 12H30 l\u00e9gales.", "avis_special": "Avis de grand frais \u00e0 coup de vent Nr 138", "echeances": [{"titre": "Situation g\u00e9n\u00e9rale le jeudi 21 octobre 2021 \u00e0 06H00 UTC, et \u00e9volution", "regions": [{"situation": "D\u00e9pression 963 hPa \u00e0 l'ouest imm\u00e9diat de la Norv\u00e8ge, \u00e9voluant peu, pr\u00e9vue 986 hPa sur la Norv\u00e8ge vendredi matin, se comblant en soir\u00e9e.\nAnticyclone 1029 au large de l'Espagne se decalant sur l'ouest de la France vendredi."}]}, {"titre": "Observations le jeudi 21 octobre 2021 \u00e0 09H00 UTC", "regions": [{"observations": [{"observation": "Dunkerque : vent Ouest 21 n\u0153uds, rafales 41 n\u0153uds,  mer agit\u00e9e,  1005 hPa en hausse,  tr\u00e8s nuageux \u00e0 couvert,  visibilit\u00e9 5 milles.\nCap Gris Nez : vent Ouest 31 n\u0153uds.\nBoulogne : vent Ouest-Nord-Ouest 23 n\u0153uds, rafales 45 n\u0153uds,  mer forte,  1006 hPa en hausse,  tr\u00e8s nuageux \u00e0 couvert,  visibilit\u00e9 6 milles."}]}]}, {"titre": "Pr\u00e9visions pour l'apr\u00e8s-midi du jeudi 21 octobre", "regions": [{"previsions": {"vent": "Nord-Ouest 5 \u00e0 6. Rafales.", "mer": "agit\u00e9e \u00e0 forte, s'att\u00e9nuant agit\u00e9e.", "houle": "Ouest Sud-Ouest 1.5 \u00e0 2 m, s'att\u00e9nuant 0.5 \u00e0 1 m en Manche. Nord 0.5 \u00e0 1 m en Mer du Nord en fin de journ\u00e9e.", "temps": "nuageux.", "visibilite": "bonne."}}]}, {"titre": "Pr\u00e9visions pour la nuit du jeudi 21 octobre au vendredi 22 octobre", "regions": [{"previsions": {"vent": "Nord-Ouest 4 \u00e0 5, fra\u00eechissant Ouest \u00e0 Nord-Ouest 5 \u00e0 6 en seconde partie de nuit. Rafales.", "mer": "peu agit\u00e9e \u00e0 agit\u00e9e.", "houle": "Ouest 0,5 \u00e0 1 m en Manche, Nord 0,5 \u00e0 1.5 m en Mer du Nord.", "temps": "nuageux.", "visibilite": "bonne."}}]}, {"titre": "Pr\u00e9visions pour la journ\u00e9e du vendredi 22 octobre", "regions": [{"previsions": {"vent": "Ouest \u00e0 Nord-Ouest 5 \u00e0 6, mollissant 4 \u00e0 5 l'apr\u00e8s-midi. Rafales.", "mer": "peu agit\u00e9e \u00e0 agit\u00e9e.", "houle": "Sud-Ouest 0,5 \u00e0 1 m en Manche, Nord 0,5 \u00e0 1 m en Mer du Nord.", "temps": "nuageux.", "visibilite": "bonne."}}]}, {"titre": "Tendance pour la nuit du 22  au 23, et la journ\u00e9e du samedi 23 octobre", "regions": [{"previsions": {"vent": "mollissant rapidement Nord-Ouest 3 \u00e0 4, et Variable 1 \u00e0 3 en seconde partie de nuit, puis fra\u00eechissant Sud 3 \u00e0 4 en fin de journ\u00e9e.", "mer": "peu agit\u00e9e \u00e0 agit\u00e9e, s'att\u00e9nuant peu agit\u00e9e en seconde partie de nuit, puis belle \u00e0 peu agit\u00e9e en journ\u00e9e.", "houle": "\n- en mer du Nord : Nord 0.5 \u00e0 1 m.\n- en Manche : Ouest 0.5 \u00e0 1 m, s'amortissant \u00e0 la mi-journ\u00e9e.", "temps": "nuageux, brumes en seconde partie de nuit.", "visibilite": "bonne, localement mauvaise par brumes."}}]}], "pied": "Prochain bulletin le jeudi 21 octobre 2021, vers 18H15 l\u00e9gales"}, {"code": "BMRCOTE-01-02", "code_cote": "01", "url_meteofrance": "https://meteofrance.com/meteo-marine/baie-de-somme-cap-de-la-hague/BMSCOTE-01-02", "nom": "De la baie de Somme au cap de La Hague", "map_filename": "", "map_url": "", "titre": "Bulletin c\u00f4te \"Baie de Somme - La Hague\" midi", "chapeau": "Origine M\u00e9t\u00e9o-France. \nBulletin c\u00f4tier pour la bande des 20 milles, de la baie de Somme au cap de la Hague, du jeudi 21 octobre 2021 \u00e0 12H30 l\u00e9gales.", "avis_special": "Avis de grand frais \u00e0 coup de vent Nr 167", "echeances": [{"titre": "Situation g\u00e9n\u00e9rale le jeudi 21 octobre 2021 \u00e0 06H00 UTC, et \u00e9volution", "regions": [{"situation": "D\u00e9pression 963 hPa \u00e0 l'ouest imm\u00e9diat de la Norv\u00e8ge, \u00e9voluant peu, pr\u00e9vue 986 hPa sur la Norv\u00e8ge vendredi matin, se comblant en soir\u00e9e.\nAnticyclone 1029 au large de l'Espagne se decalant sur l'ouest de la France vendredi."}]}, {"titre": "Observations le jeudi 21 octobre 2021 \u00e0 09H00 UTC", "regions": [{"observations": [{"observation": "Cap de la Hague : vent Nord-Nord-Ouest 21 n\u0153uds, rafales 31 n\u0153uds,  1009 hPa en hausse,  visibilit\u00e9 7 milles.\nBerni\u00e8res : vent Sud-Ouest 4 n\u0153uds.\nCap de la H\u00e8ve : vent Ouest-Sud-Ouest 16 n\u0153uds, rafales 45 n\u0153uds.\nDieppe : vent Sud-Ouest 14 n\u0153uds, rafales 25 n\u0153uds,  mer agit\u00e9e,  1008 hPa en hausse,  couvert, pluies ou bruines,  visibilit\u00e9 2 milles.\nCayeux sur mer : vent Ouest 25 n\u0153uds."}]}]}, {"titre": "Pr\u00e9visions pour l'apr\u00e8s-midi du jeudi 21 octobre", "regions": [{"previsions": {"vent": "Nord \u00e0 Nord-Ouest 5 \u00e0 6, mollissant Nord 4 \u00e0 5.", "mer": "agit\u00e9e \u00e0 forte, s'att\u00e9nuant agit\u00e9e, localement peu agit\u00e9e en baie de Seine.", "houle": "\n- en baie de Seine : Nord-Ouest 0.5 \u00e0 1 m.\n- ailleurs : Ouest 1,5 \u00e0 2 m.", "temps": "nuageux.", "visibilite": "bonne."}}]}, {"titre": "Pr\u00e9visions pour la nuit du jeudi 21 octobre au vendredi 22 octobre", "regions": [{"previsions": {"vent": "secteur Nord-Ouest 3 \u00e0 4, fra\u00eechissant 4 \u00e0 5 en fin de nuit.", "mer": "peu agit\u00e9e \u00e0 agit\u00e9e.", "houle": "\n- en baie de Seine : Nord 0.5 \u00e0 1 m, s'amortissant en fin de nuit.\n- ailleurs : Ouest 1 \u00e0 1,5 m, jusqu'\u00e0 2 m sur nord Cotentin au d\u00e9but.", "temps": "peu nuageux.", "visibilite": "bonne."}}]}, {"titre": "Pr\u00e9visions pour la journ\u00e9e du vendredi 22 octobre", "regions": [{"previsions": {"vent": "Nord-Ouest 4 \u00e0 5, fra\u00eechissant rapidement 5 \u00e0 6 de la Baie de Somme au Havre jusqu'en milieu d'apr\u00e8s-midi.", "mer": "peu agit\u00e9e \u00e0 agit\u00e9e.", "houle": "\n- en baie de Seine : non significative.\n- ailleurs : Ouest 0,5 \u00e0 1 m.", "temps": "nuageux \u00e0 tr\u00e8s nuageux.", "visibilite": "bonne"}}]}, {"titre": "Tendance pour la nuit du 22  au 23, et la journ\u00e9e du samedi 23 octobre", "regions": [{"previsions": {"vent": "mollissant rapidement Nord \u00e0 Nord-Ouest 3 \u00e0 4, et Variable 1 \u00e0 3 en fin de nuit, puis s'orientant secteur Sud 3 \u00e0 4 \u00e0 la mi-journ\u00e9e.", "mer": "peu agit\u00e9e, localement agit\u00e9e au d\u00e9but, s'att\u00e9nuant belle \u00e0 peu agit\u00e9e en fin de nuit.", "houle": "Ouest 0.5 \u00e0 1 m, s'amortissant le matin.", "temps": "averses la nuit, nuageux.", "visibilite": "bonne, localement moyenne sous averses."}}]}], "pied": "Prochain bulletin le jeudi 21 octobre 2021, vers 18H15 l\u00e9gales"}, {"code": "BMRCOTE-01-03", "code_cote": "01", "url_meteofrance": "https://meteofrance.com/meteo-marine/cap-de-la-hague-penmarc-h/BMSCOTE-01-03", "nom": "Du cap de La Hague \u00e0 Penmarc\u2019h", "map_filename": "", "map_url": "", "titre": "Bulletin c\u00f4te \"La Hague \u2013 Penmarc'h\" midi", "chapeau": "Origine M\u00e9t\u00e9o-France. \nBulletin c\u00f4tier pour la bande des 20 milles, du cap de la Hague \u00e0 la pointe de Penmarc'h, du jeudi 21 octobre 2021 \u00e0 12H30 l\u00e9gales.", "avis_special": "Avis de grand frais Nr 190", "echeances": [{"titre": "Situation g\u00e9n\u00e9rale le jeudi 21 octobre 2021 \u00e0 06H00 UTC, et \u00e9volution", "regions": [{"situation": "D\u00e9pression 963 hPa \u00e0 l'ouest imm\u00e9diat de la Norv\u00e8ge, \u00e9voluant peu, pr\u00e9vue 986 hPa sur la Norv\u00e8ge vendredi matin, se comblant en soir\u00e9e.\nAnticyclone 1029 au large de l'Espagne se decalant sur l'ouest de la France vendredi."}]}, {"titre": "Observations le jeudi 21 octobre 2021 \u00e0 09H00 UTC", "regions": [{"observations": [{"observation": "Ouessant : vent Nord-Ouest 17 n\u0153uds, rafales 27 n\u0153uds,  mer forte,  1013 hPa en hausse,  clair ou peu nuageux,  visibilit\u00e9 8 milles.\nBatz : vent Ouest-Nord-Ouest 19 n\u0153uds,  visibilit\u00e9 9 milles.\nBrignogan : vent Ouest-Nord-Ouest 17 n\u0153uds, rafales 31 n\u0153uds,  mer agit\u00e9e,  visibilit\u00e9 8 milles.\nBr\u00e9hat : vent Nord-Ouest 19 n\u0153uds,  visibilit\u00e9 9 milles.\nCap de la Hague : vent Nord-Nord-Ouest 21 n\u0153uds, rafales 31 n\u0153uds,  1009 hPa en hausse,  visibilit\u00e9 7 milles.\nPointe du Raz : vent Nord-Ouest 27 n\u0153uds, rafales 39 n\u0153uds."}]}]}, {"titre": "Pr\u00e9visions pour l'apr\u00e8s-midi du jeudi 21 octobre", "regions": [{"previsions": {"vent": "Nord 4 \u00e0 5, localement 6 sur la pointe Bretagne au d\u00e9but. Rafales.", "mer": "- de Flamanville \u00e0 Br\u00e9hat : peu agit\u00e9e \u00e0 agit\u00e9e.\n- ailleurs : forte \u00e0 tr\u00e8s forte, s'att\u00e9nuant forte en fin de journ\u00e9e.", "houle": "\n- de Flamanville \u00e0 Br\u00e9hat : Ouest 0.5 \u00e0 1 m.\n- ailleurs : Ouest 3 \u00e0 4 m, s'att\u00e9nuant 2 \u00e0 3.5 m.", "temps": "\u00e9claircies.demain", "visibilite": "bonne."}}]}, {"titre": "Pr\u00e9visions pour la nuit du jeudi 21 octobre au vendredi 22 octobre", "regions": [{"previsions": {"vent": "Nord 4 \u00e0 5, mollissant Nord \u00e0 Nord-Ouest 2 \u00e0 4 en milieu de nuit.", "mer": "\n- de Flamanville \u00e0 Br\u00e9hat : peu agit\u00e9e \u00e0 agit\u00e9e.\n- ailleurs : agit\u00e9e \u00e0 forte, s'att\u00e9nuant agit\u00e9e en fin de nuit.", "houle": "\n- de Flamanville \u00e0 Br\u00e9hat : Ouest 0.5 \u00e0 1 m.\n- ailleurs : Ouest 2 \u00e0 3 m, s'att\u00e9nuant 2 m en fin de nuit.", "temps": "nuageux.", "visibilite": "bonne."}}]}, {"titre": "Pr\u00e9visions pour la journ\u00e9e du vendredi 22 octobre", "regions": [{"previsions": {"vent": "- de Flamanville \u00e0 Br\u00e9hat : Nord-Ouest 4 \u00e0 5.\n- de Br\u00e9hat \u00e0 Penmarc'h : Nord-Ouest 2 \u00e0 4.", "mer": "peu agit\u00e9e \u00e0 agit\u00e9e.", "houle": "\n- de Flamanville \u00e0 Br\u00e9hat : Ouest 0.5 \u00e0 1 m.\n- ailleurs : Ouest 2 m, s'att\u00e9nuant 1 \u00e0 1,5 m l'apr\u00e8s-midi.", "temps": "nuageux \u00e0 tr\u00e8s nuageux.", "visibilite": "bonne."}}]}, {"titre": "Tendance pour la nuit du 22  au 23, et la journ\u00e9e du samedi 23 octobre", "regions": [{"previsions": {"vent": "Variable 1 \u00e0 3, localement Nord-Ouest 3 \u00e0 4 le long du Cotentin au d\u00e9but, fra\u00eechissant Sud 3 \u00e0 4 en fin de nuit, puis 4 \u00e0 5 sur la pointe Bretagne l'apr\u00e8s-midi.", "mer": "peu agit\u00e9e \u00e0 agit\u00e9e, s'att\u00e9nuant peu agit\u00e9e en seconde partie de nuit, localement belle de Flamanville \u00e0 Br\u00e9hat.", "houle": "Ouest 0.5 \u00e0 1.5 m, s'att\u00e9nuant 0.5 \u00e0 1 m le matin.", "temps": "tr\u00e8s nuageux \u00e0 couvert.", "visibilite": "bonne."}}]}], "pied": "Prochain bulletin le jeudi 21 octobre 2021, vers 18H15 l\u00e9gales"}, {"code": "BMRCOTE-01-04", "code_cote": "01", "url_meteofrance": "https://meteofrance.com/meteo-marine/penmarc-h-anse-de-l-aiguillon/BMSCOTE-01-04", "nom": "De Penmarc\u2019h \u00e0 l\u2019Anse de l\u2019Aiguillon", "map_filename": "", "map_url": "", "titre": "Bulletin c\u00f4te \"Penmarc'h \u2013 Aiguillon\" midi", "chapeau": "Origine M\u00e9t\u00e9o-France. \nBulletin c\u00f4tier pour la bande des 20 milles, de la pointe de Penmarc'h \u00e0 l'anse de l'Aiguillon, du jeudi 21 octobre 2021 \u00e0 12H30 l\u00e9gales.", "avis_special": "Avis de grand frais Nr 87", "echeances": [{"titre": "Situation g\u00e9n\u00e9rale le jeudi 21 octobre 2021 \u00e0 06H00 UTC, et \u00e9volution", "regions": [{"situation": "D\u00e9pression 963 hPa \u00e0 l'ouest imm\u00e9diat de la Norv\u00e8ge, \u00e9voluant peu, pr\u00e9vue 986 hPa sur la Norv\u00e8ge vendredi matin, se comblant en soir\u00e9e.\nAnticyclone 1029 au large de l'Espagne se decalant sur l'ouest de la France vendredi."}]}, {"titre": "Observations le jeudi 21 octobre 2021 \u00e0 09H00 UTC", "regions": [{"observations": [{"observation": "Pointe de Penmarc'h : vent Ouest 29 n\u0153uds, rafales 47 n\u0153uds,  averses et grains,  visibilit\u00e9 800 m\u00e8tres.\nBelle Ile : vent Ouest 27 n\u0153uds, rafales 43 n\u0153uds,  1014 hPa en hausse,  tr\u00e8s nuageux \u00e0 couvert,  visibilit\u00e9 6 milles.\nIle d'Yeu : vent Ouest 12 n\u0153uds, rafales 27 n\u0153uds,  mer forte,  1016 hPa en hausse,  clair ou peu nuageux,  visibilit\u00e9 8 milles.\nGroix : vent Ouest-Sud-Ouest 27 n\u0153uds, rafales 45 n\u0153uds,  mer forte,  visibilit\u00e9 4 milles.\nPointe de Chemoulin : vent Ouest 29 n\u0153uds,  mer agit\u00e9e,  tr\u00e8s nuageux \u00e0 couvert,  visibilit\u00e9 5 milles."}]}]}, {"titre": "Pr\u00e9visions pour l'apr\u00e8s-midi du jeudi 21 octobre", "regions": [{"previsions": {"vent": "Ouest \u00e0 Nord-Ouest 5 \u00e0 6, virant progressivement Nord 4 \u00e0 5 par l'ouest. Rafales.", "mer": "forte \u00e0 tr\u00e8s forte, s'att\u00e9nuant agit\u00e9e \u00e0 forte en soir\u00e9e.", "houle": "Ouest 3 \u00e0 4 m.", "temps": "averses.", "visibilite": "moyenne sous pr\u00e9cipitations."}}]}, {"titre": "Pr\u00e9visions pour la nuit du jeudi 21 octobre au vendredi 22 octobre", "regions": [{"previsions": {"vent": "Nord \u00e0 Nord-Est 4 \u00e0 5, mollissant 3 \u00e0 4 en fin de nuit.", "mer": "agit\u00e9e \u00e0 forte, s'att\u00e9nuant agit\u00e9e en fin de nuit.", "houle": "Ouest 3 m, s'att\u00e9nuant 2 m en fin de nuit.", "temps": "peu nuageux \u00e0 nuageux, quelques averses au d\u00e9but.", "visibilite": "bonne, localement moyenne sous averses."}}]}, {"titre": "Pr\u00e9visions pour la journ\u00e9e du vendredi 22 octobre", "regions": [{"previsions": {"vent": "secteur Nord 2 \u00e0 4.", "mer": "peu agit\u00e9e \u00e0 agit\u00e9e.", "houle": "Ouest 1.5 \u00e0 2 m, s'att\u00e9nuant 0.5 \u00e0 1.5 m en fin de journ\u00e9e.", "temps": "\u00e9claircies le matin, puis nuageux par le nord.", "visibilite": "bonne."}}]}, {"titre": "Tendance pour la nuit du 22  au 23, et la journ\u00e9e du samedi 23 octobre", "regions": [{"previsions": {"vent": "Variable 1 \u00e0 3, fra\u00eechissant Sud-Est 3 \u00e0 4 le matin.", "mer": "peu agit\u00e9e, parfois agit\u00e9e au d\u00e9but.", "houle": "Ouest 0.5 \u00e0 1.5 m, s'att\u00e9nuant 0.5 \u00e0 1 m le matin.", "temps": "nuageux la nuit, ensoleill\u00e9 en journ\u00e9e.", "visibilite": "bonne."}}]}], "pied": "Prochain bulletin le jeudi 21 octobre 2021, vers 18H15 l\u00e9gales"}, {"code": "BMRCOTE-01-05", "code_cote": "01", "url_meteofrance": "https://meteofrance.com/meteo-marine/anse-de-l-aiguillon-frontiere-espagnole/BMSCOTE-01-05", "nom": "De l\u2019Anse de l\u2019Aiguillon \u00e0 la fronti\u00e8re espagnole", "map_filename": "", "map_url": "", "titre": "Bulletin c\u00f4te \"Aiguillon - Fronti\u00e8re espagnole\" midi", "chapeau": "Origine M\u00e9t\u00e9o-France. \nBulletin c\u00f4tier pour la bande des 20 milles, de l'anse de l'Aiguillon \u00e0 la fronti\u00e8re espagnole, du jeudi 21 octobre 2021 \u00e0 12H30 l\u00e9gales.", "avis_special": "Pas d'avis de vent fort en cours ni pr\u00e9vu.", "echeances": [{"titre": "Situation g\u00e9n\u00e9rale le jeudi 21 octobre 2021 \u00e0 06H00 UTC, et \u00e9volution", "regions": [{"situation": "D\u00e9pression 963 hPa \u00e0 l'ouest imm\u00e9diat de la Norv\u00e8ge, \u00e9voluant peu, pr\u00e9vue 986 hPa sur la Norv\u00e8ge vendredi matin, se comblant en soir\u00e9e.\nAnticyclone 1029 au large de l'Espagne se decalant sur l'ouest de la France vendredi."}]}, {"titre": "Observations le jeudi 21 octobre 2021 \u00e0 09H00 UTC", "regions": [{"observations": [{"observation": "St Cl\u00e9ment des Baleines : vent Ouest-Sud-Ouest 16 n\u0153uds, rafales 31 n\u0153uds.\nPointe de Chassiron : vent Ouest-Sud-Ouest 16 n\u0153uds, rafales 27 n\u0153uds,  1018 hPa en hausse,  visibilit\u00e9 7 milles.\nCap Ferret : vent Ouest-Sud-Ouest 12 n\u0153uds, rafales 25 n\u0153uds.\nPointe de Socoa : vent Sud-Sud-Ouest 8 n\u0153uds,  mer agit\u00e9e,  1022 hPa en hausse,  tr\u00e8s nuageux \u00e0 couvert,  visibilit\u00e9 6 milles."}]}]}, {"titre": "Pr\u00e9visions pour l'apr\u00e8s-midi du jeudi 21 octobre", "regions": [{"previsions": {"vent": "secteur Ouest 4 \u00e0 5, localement 6 sur c\u00f4te Charente. Rafales.", "mer": "forte.", "houle": "Ouest \u00e0 Nord-Ouest 3 \u00e0 4 m, s'att\u00e9nuant 3 \u00e0 3.5 m.", "temps": "averses.", "visibilite": "moyenne sous averses."}}]}, {"titre": "Pr\u00e9visions pour la nuit du jeudi 21 octobre au vendredi 22 octobre", "regions": [{"previsions": {"vent": "Ouest \u00e0 Nord-Ouest 4 \u00e0 5, virant Nord \u00e0 Nord-Est en milieu de nuit.", "mer": "forte, s'att\u00e9nuant agit\u00e9e \u00e0 forte au nord d'Arcachon en seconde partie de nuit.", "houle": "Ouest \u00e0 Nord-Ouest 3 \u00e0 3.5 m, s'att\u00e9nuant 2.5 \u00e0 3 m.", "temps": "averses.", "visibilite": "moyenne sous averses."}}]}, {"titre": "Pr\u00e9visions pour la journ\u00e9e du vendredi 22 octobre", "regions": [{"previsions": {"vent": "secteur Nord 4 \u00e0 5.", "mer": "agit\u00e9e \u00e0 forte, s'att\u00e9nuant agit\u00e9e \u00e0 la mi-journ\u00e9e.", "houle": "Nord-Ouest 2 \u00e0 2.5 m, s'att\u00e9nuant 1.5 \u00e0 2 m en fin de journ\u00e9e.", "temps": "averses au sud de Messanges.", "visibilite": "bonne, localement moyenne sous averses."}}]}, {"titre": "Tendance pour la nuit du 22  au 23, et la journ\u00e9e du samedi 23 octobre", "regions": [{"previsions": {"vent": "Nord-Est 4 \u00e0 5, mollissant Est \u00e0 Nord-Est 3 \u00e0 4 en seconde partie de nuit, puis Variable 1 \u00e0 3 sur c\u00f4te basque le matin.", "mer": "agit\u00e9e, s'att\u00e9nuant progressivement peu agit\u00e9e par le nord.", "houle": "Ouest \u00e0 Nord-Ouest 1 \u00e0 2 m, s'att\u00e9nuant 0.5 \u00e0 1 m en journ\u00e9e.", "temps": "peu nuageux la nuit, ensoleill\u00e9 en journ\u00e9e.", "visibilite": "bonne."}}]}], "pied": "Prochain bulletin le jeudi 21 octobre 2021, vers 18H15 l\u00e9gales"}, {"code": "BMRCOTE-02-01", "code_cote": "02", "url_meteofrance": "https://meteofrance.com/meteo-marine/frontiere-espagnole-port-camargue/BMSCOTE-02-01", "nom": "De la fronti\u00e8re espagnole \u00e0 Port Camargue", "map_filename": "", "map_url": "", "titre": "Bulletin c\u00f4te \"Fronti\u00e8re espagnole - Port Camargue\" midi", "chapeau": "Origine M\u00e9t\u00e9o-France. \nBulletin c\u00f4tier pour la bande des 20 milles, de la fronti\u00e8re espagnole \u00e0 Port-Camargue, du jeudi 21 octobre 2021 \u00e0 12H30 l\u00e9gales.", "avis_special": "Pas d'avis de vent fort en cours ni pr\u00e9vu.", "echeances": [{"titre": "Situation g\u00e9n\u00e9rale le jeudi 21 octobre 2021 \u00e0 06H00 UTC, et \u00e9volution", "regions": [{"situation": "D\u00e9pression 1014 hPa \u00e0 l'ouest du Golfe du Lion, se d\u00e9calant vers l'ouest, pr\u00e9vue 1010 hPa sur la Mer Ligure cet apr\u00e8s-midi, et quasi-stationnaire. \nHautes pressions s'affaissant vers 1017 hPa au sud du bassin, puis autour de 1015 hPa cette nuit."}]}, {"titre": "Observations le jeudi 21 octobre 2021 \u00e0 09H00 UTC", "regions": [{"observations": [{"observation": "S\u00e8te : vent Nord-Nord-Ouest 10 n\u0153uds, 1019 hPa en hausse.\nCap B\u00e9ar : vent Nord-Ouest 21 n\u0153uds, rafales 37 n\u0153uds, mer peu agit\u00e9e, 1018 hPa en hausse, tr\u00e8s nuageux \u00e0 couvert, visibilit\u00e9 10 milles.\nLeucate : vent Nord-Ouest 12 n\u0153uds, rafales 25 n\u0153uds, mer belle, 1019 hPa en hausse, tr\u00e8s nuageux \u00e0 couvert, visibilit\u00e9 5 milles.\nEspiguette : vent Nord-Ouest 8 n\u0153uds."}]}]}, {"titre": "Pr\u00e9visions pour l'apr\u00e8s-midi du jeudi 21 octobre", "regions": [{"previsions": {"vent": "Nord-Ouest 4 \u00e0 5, localement 6 vers la c\u00f4te Vermeille. Rafales.", "mer": "peu agit\u00e9e.", "houle": "non significative.", "temps": "ciel devenant peu nuageux.", "visibilite": "bonne."}}]}, {"titre": "Pr\u00e9visions pour la nuit du jeudi 21 octobre au vendredi 22 octobre", "regions": [{"previsions": {"vent": "Nord-Ouest 4 \u00e0 5 fra\u00eechissant 5 \u00e0 6 en fin de soir\u00e9e. Rafales.", "mer": "peu agit\u00e9e, localement agit\u00e9e vers le large au sud de Leucate en milieu de nuit.", "houle": "non significative.", "temps": "peu nuageux, mais localement nuageux \u00e0 tr\u00e8s nuageux au sud de Gruissan jusqu'en milieu de nuit.", "visibilite": "bonne."}}]}, {"titre": "Pr\u00e9visions pour la journ\u00e9e du vendredi 22 octobre", "regions": [{"previsions": {"vent": "Nord \u00e0 Nord-Ouest 5 \u00e0 6, localement 7 au sud de Gruissan l'apr\u00e8s-midi. Rafales.", "mer": "peu agit\u00e9e, localement agit\u00e9e vers le large au sud de Leucate.", "houle": "non significative.", "temps": "ensoleill\u00e9.", "visibilite": "bonne."}}]}, {"titre": "Tendance pour la nuit du 22  au 23, et la journ\u00e9e du samedi 23 octobre", "regions": [{"previsions": {"vent": "Nord \u00e0 Nord-Ouest 5 \u00e0 6, localement 7 au sud de Gruissan, mollissant Nord 4 \u00e0 5 en matin\u00e9e puis Nord \u00e0 Nord-Est 2 \u00e0 4 l'apr\u00e8s-midi.", "mer": "peu agit\u00e9e \u00e0 agit\u00e9e, devenant belle \u00e0 peu agit\u00e9e en journ\u00e9e.", "houle": "non significative.", "temps": "ciel clair \u00e0 peu nuageux.", "visibilite": "bonne."}}]}], "pied": "Prochain bulletin le jeudi 21 octobre 2021, vers 18H15 l\u00e9gales"}, {"code": "BMRCOTE-02-02", "code_cote": "02", "url_meteofrance": "https://meteofrance.com/meteo-marine/port-camargue-saint-raphael/BMSCOTE-02-02", "nom": "De Port Camargue \u00e0 Saint-Rapha\u00ebl", "map_filename": "cote-02-02.png", "map_url": "https://umap.openstreetmap.fr/en/map/port-camargue-a-sainte-maxime_659137#", "titre": "Bulletin c\u00f4te \"Port Camargue - Saint Rapha\u00ebl\" midi", "chapeau": "Origine M\u00e9t\u00e9o-France. \nBulletin c\u00f4tier pour la bande des 20 milles, de Port-Camargue \u00e0 Saint-Rapha\u00ebl, du jeudi 21 octobre 2021 \u00e0 12H30 l\u00e9gales.", "avis_special": "Pas d'avis de vent fort en cours ni pr\u00e9vu.", "echeances": [{"titre": "Situation g\u00e9n\u00e9rale le jeudi 21 octobre 2021 \u00e0 06H00 UTC, et \u00e9volution", "regions": [{"situation": "D\u00e9pression 1014 hPa \u00e0 l'ouest du Golfe du Lion, se d\u00e9calant vers l'ouest, pr\u00e9vue 1010 hPa sur la Mer Ligure cet apr\u00e8s-midi, et quasi-stationnaire. \nHautes pressions s'affaissant vers 1017 hPa au sud du bassin, puis autour de 1015 hPa cette nuit."}]}, {"titre": "Observations le jeudi 21 octobre 2021 \u00e0 09H00 UTC", "regions": [{"observations": [{"observation": "Cap Camarat : vent Ouest-Sud-Ouest 4 n\u0153uds, tr\u00e8s nuageux \u00e0 couvert, visibilit\u00e9 10 milles.\nCap Cepet : vent Est 4 n\u0153uds, rafales 17 n\u0153uds, mer belle, tr\u00e8s nuageux \u00e0 couvert,  visibilit\u00e9 6 milles.\nPorquerolles : vent Ouest 6 n\u0153uds.\nCap Couronne : vent Ouest-Nord-Ouest 10 n\u0153uds."}]}]}, {"titre": "Pr\u00e9visions pour l'apr\u00e8s-midi du jeudi 21 octobre", "regions": [{"previsions": {"vent": "\n- de Port Camargue au Levant : Nord-Ouest 5 \u00e0 6. Rafales.\n- du Levant \u00e0 Saint-Rapha\u00ebl : Sud-Ouest 2 \u00e0 4, virant Ouest 4 \u00e0 5 en milieu d'apr\u00e8s-midi, parfois 6.", "mer": "peu agit\u00e9e \u00e0 agit\u00e9e.", "houle": "Sud-Ouest autour de 1 m, s'amortissant par l'ouest.", "temps": "ciel devenant peu nuageux, quelques averses \u00e0 lest de Toulon en d\u00e9but d'apr\u00e8s-midi.", "visibilite": "bonne, parfois moyenne sous averses."}}]}, {"titre": "Pr\u00e9visions pour la nuit du jeudi 21 octobre au vendredi 22 octobre", "regions": [{"previsions": {"vent": "Ouest \u00e0 Nord-Ouest 5 \u00e0 6, mollissant 4 \u00e0 5 \u00e0 l'est de Porquerolles en fin de nuit. Rafales.", "mer": "peu agit\u00e9e \u00e0 agit\u00e9e.", "houle": "non significative. S'\u00e9tablissant ouest 1 \u00e0 1,5 m au sud des iles d'Hy\u00e8res en fin de nuit.", "temps": "ciel peu nuageux.", "visibilite": "bonne."}}]}, {"titre": "Pr\u00e9visions pour la journ\u00e9e du vendredi 22 octobre", "regions": [{"previsions": {"vent": "\n- de Port Camargue \u00e0 Porquerolles : Nord \u00e0 Nord-Ouest 5 \u00e0 6, localement 7 de Fos \u00e0 La Ciotat l'apr\u00e8s-midi. Rafales.\n- de Porquerolles \u00e0 Saint-Rapha\u00ebl : Nord-Ouest mollissant 2 \u00e0 4, devenant Variable 1 \u00e0 3 l'apr\u00e8s-midi.", "mer": "peu agit\u00e9e \u00e0 agit\u00e9e.", "houle": "\n- \u00e0 l'ouest de Sici\u00e9 : non significative.\n- \u00e0 l'est de Sici\u00e9 : Ouest 1 \u00e0 1.5 m.", "temps": "ciel peu nuageux.", "visibilite": "bonne."}}]}, {"titre": "Tendance pour la nuit du 22  au 23, et la journ\u00e9e du samedi 23 octobre", "regions": [{"previsions": {"vent": "\n- de Port Camargue \u00e0 Toulon : Nord \u00e0 Nord-Ouest 6 \u00e0 7, mollissant Nord 4 \u00e0 5 le matin puis 3 \u00e0 4 l'apr\u00e8s-midi mais virant Est 4 \u00e0 5 de Marseille \u00e0 Toulon. Rafales.\n- de Toulon \u00e0 Saint-Rapha\u00ebl : s'orientant secteur Nord-Est 3 \u00e0 4 la nuit, fra\u00eechissant Est \u00e0 Nord-Est 4 \u00e0 5 en journ\u00e9e.", "mer": "peu agit\u00e9e \u00e0 agit\u00e9e.", "houle": "Ouest 1 \u00e0 1.5 m au sud des \u00eeles d'Hy\u00e8res s'amortissant.", "temps": "ciel peu nuageux.", "visibilite": "bonne."}}]}], "pied": "Prochain bulletin le jeudi 21 octobre 2021, vers 18H15 l\u00e9gales"}, {"code": "BMRCOTE-02-03", "code_cote": "02", "url_meteofrance": "https://meteofrance.com/meteo-marine/saint-raphael-menton/BMSCOTE-02-03", "nom": "De Saint-Rapha\u00ebl \u00e0 Menton", "map_filename": "", "map_url": "", "titre": "Bulletin c\u00f4te \"Saint Rapha\u00ebl \u2013 Menton\" midi", "chapeau": "Origine M\u00e9t\u00e9o-France. \nBulletin c\u00f4tier pour la bande des 20 milles, de Saint-Rapha\u00ebl \u00e0 Menton, du jeudi 21 octobre 2021 \u00e0 12H30 l\u00e9gales.", "avis_special": "Pas d'avis de vent fort en cours ni pr\u00e9vu.", "echeances": [{"titre": "Situation g\u00e9n\u00e9rale le jeudi 21 octobre 2021 \u00e0 06H00 UTC, et \u00e9volution", "regions": [{"situation": "D\u00e9pression 1014 hPa \u00e0 l'ouest du Golfe du Lion, se d\u00e9calant vers l'ouest, pr\u00e9vue 1010 hPa sur la Mer Ligure cet apr\u00e8s-midi, et quasi-stationnaire. \nHautes pressions s'affaissant vers 1017 hPa au sud du bassin, puis autour de 1015 hPa cette nuit."}]}, {"titre": "Observations le jeudi 21 octobre 2021 \u00e0 09H00 UTC", "regions": [{"observations": [{"observation": "Nice : vent Nord-Ouest 8 n\u0153uds,  1016 hPa en baisse, couvert, pluies ou bruines,  visibilit\u00e9 21 milles.\nLe Dramont : vent Ouest 10 n\u0153uds.\nAntibes la Garoupe : vent Ouest 4 n\u0153uds, mer belle, tr\u00e8s nuageux \u00e0 couvert, visibilit\u00e9 9 milles."}]}]}, {"titre": "Pr\u00e9visions pour l'apr\u00e8s-midi du jeudi 21 octobre", "regions": [{"previsions": {"vent": "Sud-Ouest 3 \u00e0 4, fra\u00eechissant 4 \u00e0 5 en d\u00e9but d'apr\u00e8s-midi, puis Ouest \u00e0 Sud-Ouest 5 \u00e0 6 en fin d'apr\u00e8s-midi. Rafales.", "mer": "devenant agit\u00e9e.", "houle": "Sud 0.5 \u00e0 1 m.", "temps": "ciel devenant peu nuageux, quelques averses en d\u00e9but d'apr\u00e8s-midi.", "visibilite": "bonne, parfois moyenne sous averses."}}]}, {"titre": "Pr\u00e9visions pour la nuit du jeudi 21 octobre au vendredi 22 octobre", "regions": [{"previsions": {"vent": "Ouest \u00e0 Sud-Ouest 5 \u00e0 6, devenant Variable D\u00e9pressionnaire 2 \u00e0 4 au nord d'Antibes en fin de soir\u00e9e, puis s'orientant partout Nord-Est 4 \u00e0 5 en deuxi\u00e8me partie de nuit.", "mer": "agit\u00e9e, devenant peu agit\u00e9e \u00e0 agit\u00e9e en fin de nuit.", "houle": "Sud-Ouest 0.5 \u00e0 1 m, localement 1.5 m vers le large.", "temps": "ciel peu nuageux.", "visibilite": "bonne."}}]}, {"titre": "Pr\u00e9visions pour la journ\u00e9e du vendredi 22 octobre", "regions": [{"previsions": {"vent": "Est \u00e0 Nord-Est 4 \u00e0 5, mais localement Nord-Ouest 3 \u00e0 5 vers St-Rapha\u00ebl en d\u00e9but de journ\u00e9e, mollissant 2 \u00e0 4 l'apr\u00e8s-midi.", "mer": "peu agit\u00e9e.", "houle": "Sud-Ouest 0.5 \u00e0 1 m, s'amortissant en fin de journ\u00e9e.", "temps": "bien ensoleill\u00e9.", "visibilite": "bonne."}}]}, {"titre": "Tendance pour la nuit du 22  au 23, et la journ\u00e9e du samedi 23 octobre", "regions": [{"previsions": {"vent": "Est \u00e0 Nord-Est 3 \u00e0 4, fra\u00eechissant 4 \u00e0 5 en journ\u00e9e, parfois 6 vers le large.", "mer": "belle \u00e0 peu agit\u00e9e.", "houle": "non significative.", "temps": "ciel clair \u00e0 peu nuageux.", "visibilite": "bonne."}}]}], "pied": "Prochain bulletin le jeudi 21 octobre 2021, vers 18H15 l\u00e9gales"}, {"code": "BMRCOTE-02-04", "code_cote": "02", "url_meteofrance": "https://meteofrance.com/meteo-marine/corse-corse/BMSCOTE-02-04", "nom": "Corse", "map_filename": "", "map_url": "", "titre": "Bulletin c\u00f4te \"Corse\" midi", "chapeau": "Origine M\u00e9t\u00e9o-France. \nBulletin c\u00f4tier pour la bande des 20 milles, c\u00f4te de Corse, du jeudi 21 octobre 2021 \u00e0 12H30 l\u00e9gales.", "avis_special": "Pas d'avis de vent fort en cours ni pr\u00e9vu.", "echeances": [{"titre": "Situation g\u00e9n\u00e9rale le jeudi 21 octobre 2021 \u00e0 06H00 UTC, et \u00e9volution", "regions": [{"situation": "D\u00e9pression 1014 hPa \u00e0 l'ouest du Golfe du Lion, s\u00e0 Sud-Oueste d\u00e9calant vers l'ouest, pr\u00e9vue 1010 hPa sur la Mer Ligure cet apr\u00e8s-midi, et quasi-stationnaire. \nHautes pressions s'affaissant vers 1017 hPa au sud du bassin, puis autour de 1015 hPa cette nuit."}]}, {"titre": "Observations le jeudi 21 octobre 2021 \u00e0 09H00 UTC", "regions": [{"observations": [{"observation": "Cap Corse : vent Ouest 8 n\u0153uds, 1017 hPa en hausse.\nPertusato : vent Ouest 6 n\u0153uds, rafales 19 n\u0153uds, 1018 hPa en baisse.\nLa Chiappa : vent Sud-Ouest 12 n\u0153uds, rafales 25 n\u0153uds.\nAlistro : vent Sud 2 n\u0153uds, mer belle, 1017 hPa en baisse, nuageux avec \u00e9claircies,  visibilit\u00e9 9 milles.\nCap Sagro : vent Sud 10 n\u0153uds, mer belle, nuageux avec \u00e9claircies, visibilit\u00e9 15 milles.\nIle Rousse : vent Ouest 6 n\u0153uds, 1016 hPa en hausse, nuageux avec \u00e9claircies,  visibilit\u00e9 10 milles.\nLa Parata : vent Est-Sud-Est 12 n\u0153uds, mer belle, nuageux avec \u00e9claircies, visibilit\u00e9 10 milles."}]}]}, {"titre": "Pr\u00e9visions pour l'apr\u00e8s-midi du jeudi 21 octobre", "regions": [{"previsions": {"vent": "\n- de Cargese au cap Corse : Sud \u00e0 Sud-Ouest 5 \u00e0 6. Rafales.\n- du cap Corse \u00e0 Al\u00e9ria : Sud 3 \u00e0 4, devenant Variable en fin de journ\u00e9e.\n- d'Al\u00e9ria \u00e0 Bonifacio : Sud \u00e0 Sud-Ouest 4 \u00e0 5, parfois 6. Rafales.\n- de Bonifacio \u00e0 Cargese : secteur Sud 2 \u00e0 4, virant secteur Ouest en milieu d'apr\u00e8s-midi.", "mer": "peu agit\u00e9e, localement agit\u00e9e de Scandola au Cap Corse.", "houle": "Sud 0.5 \u00e0 1 m.", "temps": "nuageux avec \u00e9claircies. Averses passag\u00e8res \u00e0 l'ouest.", "visibilite": "bonne, parfois moyenne sous averses."}}]}, {"titre": "Pr\u00e9visions pour la nuit du jeudi 21 octobre au vendredi 22 octobre", "regions": [{"previsions": {"vent": "\n- de Scandola \u00e0 Bastia : Ouest \u00e0 Sud-Ouest 5 \u00e0 6. Rafales.\n- de Bastia \u00e0 Solenzara : Variable 2 \u00e0 4, s'orientant Nord \u00e0 Nord-Est en deuxi\u00e8me partie de nuit.\n- de Solenzara \u00e0 Bonifacio : Ouest \u00e0 Sud-Ouest 5 \u00e0 6. Rafales.\n- de Bonifacio \u00e0 Scandola : Ouest \u00e0 Nord-Ouest 3 \u00e0 4, parfois 5 vers les bouches de bonifacio..", "mer": " \n- sur la c\u00f4te occidentale et extr\u00e9mit\u00e9s : peu agit\u00e9e \u00e0 agit\u00e9e, devenant agit\u00e9e en fin de nuit.\n- sur la c\u00f4te orientale : peu agit\u00e9e.", "houle": "Sud 0.5 \u00e0 1 m, s'\u00e9tablissant secteur Ouest 1 \u00e0 1.5 m sur la c\u00f4te occidentale et extr\u00e9mit\u00e9s en milieu de nuit.", "temps": "ciel nuageux.", "visibilite": "bonne."}}]}, {"titre": "Pr\u00e9visions pour la journ\u00e9e du vendredi 22 octobre", "regions": [{"previsions": {"vent": "\n- de Cargese \u00e0 l'Ile Rousse : Sud \u00e0 Sud-Ouest 5 \u00e0 6, mollissant 4 \u00e0 5 l'apr\u00e8s-midi puis 3 \u00e0 4 en soir\u00e9e.\n- de l'Ile Rousse \u00e0 La Chiappa : secteur Nord-Est 2 \u00e0 4.\n- de La Chiappa \u00e0 Senetosa : Ouest 4 \u00e0 5, localement 6 \u00e0 l'est des bouches . Rafales.\n- de Senetosa \u00e0 Cargese : Sud-Ouest dominant 2 \u00e0 4.", "mer": " \n- sur la c\u00f4te occidentale et extr\u00e9mit\u00e9s : agit\u00e9e, s\u2019att\u00e9nuant peu agit\u00e9e au nord d'Ajaccio en fin de journ\u00e9e.\n- sur la c\u00f4te orientale : peu agit\u00e9e.", "houle": "\n- sur la c\u00f4te occidentale et extr\u00e9mit\u00e9s : secteur Ouest 1 \u00e0 1.5 m.\n- sur la c\u00f4te orientale : Sud 0.5 \u00e0 1 m.", "temps": "nuageux. Averses passag\u00e8res au nord-est en mi-journ\u00e9e.", "visibilite": "bonne, moyenne sous averses."}}]}, {"titre": "Tendance pour la nuit du 22  au 23, et la journ\u00e9e du samedi 23 octobre", "regions": [{"previsions": {"vent": "devenant Variable 1 \u00e0 3 en soir\u00e9e, s'orientant Est \u00e0 Nord-Est 3 \u00e0 4 en journ\u00e9e, localement 5 sur les extr\u00e9mit\u00e9s de l'\u00eele.", "mer": "peu agit\u00e9e \u00e0 agit\u00e9e \u00e0 l'ouest, belle \u00e0 peu agit\u00e9e \u00e0 l'est.", "houle": "Ouest 1 m sur la c\u00f4te occidentale, localement 1.5 m au sud d'Ajaccio en soir\u00e9e.", "temps": "beau temps passag\u00e8rement nuageux.", "visibilite": "bonne."}}]}], "pied": "Prochain bulletin le jeudi 21 octobre 2021, vers 18H15 l\u00e9gales"}]